ppt_to_markdown_mcp/__init__.py
ppt_to_markdown_mcp/server.py
ppt_to_markdown_mcp-0.1.0.dist-info/METADATA
ppt_to_markdown_mcp-0.1.0.dist-info/WHEEL
ppt_to_markdown_mcp-0.1.0.dist-info/entry_points.txt
ppt_to_markdown_mcp-0.1.0.dist-info/RECORD
