Metadata-Version: 2.4
Name: ppt-to-markdown-mcp
Version: 0.1.0
Summary: PPT转Markdown MCP服务器 - Python版本
Requires-Python: >=3.11
Requires-Dist: markitdown[pptx]>=0.0.1a3
Requires-Dist: mcp>=1.0.0
Requires-Dist: python-pptx>=0.6.0
